aiohttp_ratelimiter-4.1.3.dist-info/licenses/LICENSE
aiohttplimiter/__init__.py
aiohttplimiter/limiter.py
aiohttplimiter/memcached_limiter.py
aiohttplimiter/memory_limiter.py
aiohttplimiter/py.typed
aiohttplimiter/redis_limiter.py
aiohttp_ratelimiter-4.1.3.dist-info/METADATA
aiohttp_ratelimiter-4.1.3.dist-info/WHEEL
aiohttp_ratelimiter-4.1.3.dist-info/top_level.txt
aiohttp_ratelimiter-4.1.3.dist-info/RECORD
