Metadata-Version: 2.4
Name: aiohttp-ratelimiter
Version: 4.1.3
Summary: A simple rate limiter for aiohttp.web
Author-email: George Luca <gluca@jgltechnologies.com>
Project-URL: Homepage, https://jgltechnologies.com/aiohttplimiter
Project-URL: Repository, https://github.com/JGLTechnologies/aiohttp-ratelimiter
Project-URL: Issues, https://github.com/JGLTechnologies/aiohttp-ratelimiter/issues
Classifier: Development Status :: 5 - Production/Stable
Classifier: Framework :: aiohttp
Classifier: Intended Audience :: Developers
Classifier: Programming Language :: Python :: 3
Classifier: Typing :: Typed
Requires-Python: >=3.7
License-File: LICENSE
Requires-Dist: aiohttp
Requires-Dist: limits
Requires-Dist: typing-extensions>=3.10.0.2
Provides-Extra: memcached
Requires-Dist: emcache; extra == "memcached"
Provides-Extra: redis
Requires-Dist: coredis; extra == "redis"
Dynamic: license-file
